{
  "filename": "egg_tart_crust_tangyuan.json",
  "name": "蛋塔皮包湯圓",
  "description": "使用現成蛋塔皮包裹湯圓，經氣炸鍋烘烤後，呈現外層酥脆、內餡流心的創意甜點。",
  "servings": {
    "quantity": 1,
    "unit": "份"
  },
  "tags": [
    "氣炸鍋料理",
    "創意點心",
    "甜點"
  ],
  "ingredients": [
    {
      "name": "冷凍蛋塔皮",
      "quantity": 100,
      "unit": "g"
    },
    {
      "name": "冷凍湯圓",
      "quantity": 80,
      "unit": "g"
    },
    {
      "name": "蛋黃",
      "quantity": 18,
      "unit": "g"
    },
    {
      "name": "黑芝麻",
      "quantity": 2,
      "unit": "g"
    }
  ],
  "steps": [
    "將冷凍湯圓包入稍微退冰的蛋塔皮中，收口捏緊搓圓。",
    "在包好的麵糰表面用牙籤或叉子輕輕扎孔，防止烘烤時爆裂。",
    "於表面均勻塗上一層蛋黃液。",
    "撒上少許黑芝麻裝飾。",
    "放入氣炸鍋中，以 170°C 烘烤 12 分鐘即可。"
  ],
  "notes": [
    "冷凍蛋塔皮：1 個約為 25 g，本食譜使用 4 個。",
    "冷凍湯圓：1 顆約為 20 g，本食譜使用 4 顆。",
    "蛋黃：1 顆約為 18 g。",
    "黑芝麻：少許標示為 2 g 以符合計量規則。",
    "烘烤時間可根據氣炸鍋品牌功率不同微調，觀察表面呈金黃色即可。"
  ]
}